graphlit_tools/__init__.py
graphlit_tools/base_tool.py
graphlit_tools/crewai_converter.py
graphlit_tools/exceptions.py
graphlit_tools/griptape_converter.py
graphlit_tools/helpers.py
graphlit_tools/extraction/__init__.py
graphlit_tools/extraction/extract_text_tool.py
graphlit_tools/extraction/extract_url_tool.py
graphlit_tools/extraction/extract_web_page_tool.py
graphlit_tools/generation/__init__.py
graphlit_tools/generation/describe_image_tool.py
graphlit_tools/generation/describe_web_page_tool.py
graphlit_tools/generation/generate_bullets_tool.py
graphlit_tools/generation/generate_chapters_tool.py
graphlit_tools/generation/generate_headlines_tool.py
graphlit_tools/generation/generate_keywords_tool.py
graphlit_tools/generation/generate_questions_tool.py
graphlit_tools/generation/generate_social_media_posts_tool.py
graphlit_tools/generation/generate_summary_tool.py
graphlit_tools/generation/prompt_tool.py
graphlit_tools/ingestion/__init__.py
graphlit_tools/ingestion/discord_ingest_tool.py
graphlit_tools/ingestion/github_issue_ingest_tool.py
graphlit_tools/ingestion/google_email_ingest_tool.py
graphlit_tools/ingestion/jira_issue_ingest_tool.py
graphlit_tools/ingestion/linear_issue_ingest_tool.py
graphlit_tools/ingestion/local_ingest_tool.py
graphlit_tools/ingestion/microsoft_email_ingest_tool.py
graphlit_tools/ingestion/microsoft_teams_ingest_tool.py
graphlit_tools/ingestion/notion_ingest_tool.py
graphlit_tools/ingestion/reddit_ingest_tool.py
graphlit_tools/ingestion/rss_ingest_tool.py
graphlit_tools/ingestion/slack_ingest_tool.py
graphlit_tools/ingestion/url_ingest_tool.py
graphlit_tools/ingestion/web_crawl_tool.py
graphlit_tools/ingestion/web_map_tool.py
graphlit_tools/ingestion/web_scrape_tool.py
graphlit_tools/ingestion/web_search_tool.py
graphlit_tools/retrieval/__init__.py
graphlit_tools/retrieval/content_retrieval_tool.py
graphlit_tools/retrieval/organization_retrieval_tool.py
graphlit_tools/retrieval/person_retrieval_tool.py
graphlit_tools-1.0.20250114004.dist-info/LICENSE
graphlit_tools-1.0.20250114004.dist-info/METADATA
graphlit_tools-1.0.20250114004.dist-info/WHEEL
graphlit_tools-1.0.20250114004.dist-info/top_level.txt
graphlit_tools-1.0.20250114004.dist-info/RECORD
