Metadata-Version: 2.2
Name: graphlit-tools
Version: 1.0.20250114004
Summary: Graphlit Agent Tools
Home-page: https://github.com/graphlit/graphlit-tools-python/
Author: Unstruk Data Inc.
Author-email: questions@graphlit.com
Requires-Python: >=3.10
License-File: LICENSE
Requires-Dist: graphlit-client
Provides-Extra: crewai
Requires-Dist: crewai; extra == "crewai"
Provides-Extra: griptape
Requires-Dist: griptape; extra == "griptape"
Dynamic: author
Dynamic: author-email
Dynamic: description
Dynamic: description-content-type
Dynamic: home-page
Dynamic: provides-extra
Dynamic: requires-dist
Dynamic: requires-python
Dynamic: summary
